[
  {
    "home_team": "NE",
    "away_team": "NYJ",
    "win_model_prediction": "NYJ",
    "home_win_prob": 0.0077969166450202465,
    "away_win_prob": 0.9922030568122864,
    "confidence": 0.9922030568122864,
    "predicted_winner": "NYJ",
    "predicted_home_score": 12.800000190734863,
    "predicted_away_score": 30.700000762939453,
    "predicted_margin": -17.90302085876465,
    "ai_spread": 17.90302085876465,
    "vegas_spread": -12.5,
    "spread_difference": 30.399999618530273,
    "total_line": 43.5,
    "key_factors": {
      "home_epa": 0,
      "away_epa": 0,
      "epa_advantage": 0,
      "home_recent_epa": 0,
      "away_recent_epa": 0
    },
    "game_id": "2025_11_NYJ_NE",
    "season": 2025,
    "week": 11,
    "game_date": "2025-11-13",
    "kickoff_time": null,
    "status": "final",
    "actual_home_score": 27,
    "actual_away_score": 14,
    "actual_winner": "NE",
    "correct": false
  },
  {
    "home_team": "NYG",
    "away_team": "GB",
    "win_model_prediction": "NYG",
    "home_win_prob": 0.7518746256828308,
    "away_win_prob": 0.2481253743171692,
    "confidence": 0.7518746256828308,
    "predicted_winner": "NYG",
    "predicted_home_score": 27.5,
    "predicted_away_score": 14.0,
    "predicted_margin": 13.519312858581543,
    "ai_spread": -13.519312858581543,
    "vegas_spread": 7.5,
    "spread_difference": -21.0,
    "total_line": 41.5,
    "key_factors": {
      "home_epa": 0,
      "away_epa": 0,
      "epa_advantage": 0,
      "home_recent_epa": 0,
      "away_recent_epa": 0
    },
    "game_id": "2025_11_GB_NYG",
    "season": 2025,
    "week": 11,
    "game_date": "2025-11-16",
    "kickoff_time": null,
    "status": "final",
    "actual_home_score": 20,
    "actual_away_score": 27,
    "actual_winner": "GB",
    "correct": false
  },
  {
    "home_team": "PIT",
    "away_team": "CIN",
    "win_model_prediction": "CIN",
    "home_win_prob": 0.02542337402701378,
    "away_win_prob": 0.9745766520500183,
    "confidence": 0.9745766520500183,
    "predicted_winner": "CIN",
    "predicted_home_score": 16.5,
    "predicted_away_score": 32.0,
    "predicted_margin": -15.565156936645508,
    "ai_spread": 15.565156936645508,
    "vegas_spread": -5.5,
    "spread_difference": 21.100000381469727,
    "total_line": 48.5,
    "key_factors": {
      "home_epa": 0,
      "away_epa": 0,
      "epa_advantage": 0,
      "home_recent_epa": 0,
      "away_recent_epa": 0
    },
    "game_id": "2025_11_CIN_PIT",
    "season": 2025,
    "week": 11,
    "game_date": "2025-11-16",
    "kickoff_time": null,
    "status": "final",
    "actual_home_score": 34,
    "actual_away_score": 12,
    "actual_winner": "PIT",
    "correct": false
  },
  {
    "home_team": "TEN",
    "away_team": "HOU",
    "win_model_prediction": "HOU",
    "home_win_prob": 0.3176679015159607,
    "away_win_prob": 0.6823320984840393,
    "confidence": 0.6823320984840393,
    "predicted_winner": "TEN",
    "predicted_home_score": 23.5,
    "predicted_away_score": 14.0,
    "predicted_margin": 9.548603057861328,
    "ai_spread": -9.548603057861328,
    "vegas_spread": 5.5,
    "spread_difference": -15.0,
    "total_line": 37.5,
    "key_factors": {
      "home_epa": 0,
      "away_epa": 0,
      "epa_advantage": 0,
      "home_recent_epa": 0,
      "away_recent_epa": 0
    },
    "game_id": "2025_11_HOU_TEN",
    "season": 2025,
    "week": 11,
    "game_date": "2025-11-16",
    "kickoff_time": null,
    "status": "final",
    "actual_home_score": 13,
    "actual_away_score": 16,
    "actual_winner": "HOU",
    "correct": false
  },
  {
    "home_team": "ARI",
    "away_team": "SF",
    "win_model_prediction": "SF",
    "home_win_prob": 0.36208105087280273,
    "away_win_prob": 0.6379189491271973,
    "confidence": 0.6379189491271973,
    "predicted_winner": "ARI",
    "predicted_home_score": 27.700000762939453,
    "predicted_away_score": 20.799999237060547,
    "predicted_margin": 6.996731281280518,
    "ai_spread": -6.996731281280518,
    "vegas_spread": 3.5,
    "spread_difference": -10.5,
    "total_line": 48.5,
    "key_factors": {
      "home_epa": 0,
      "away_epa": 0,
      "epa_advantage": 0,
      "home_recent_epa": 0,
      "away_recent_epa": 0
    },
    "game_id": "2025_11_SF_ARI",
    "season": 2025,
    "week": 11,
    "game_date": "2025-11-16",
    "kickoff_time": null,
    "status": "final",
    "actual_home_score": 22,
    "actual_away_score": 41,
    "actual_winner": "SF",
    "correct": false
  },
  {
    "home_team": "LA",
    "away_team": "SEA",
    "win_model_prediction": "SEA",
    "home_win_prob": 0.2055610567331314,
    "away_win_prob": 0.7944389581680298,
    "confidence": 0.7944389581680298,
    "predicted_winner": "SEA",
    "predicted_home_score": 24.299999237060547,
    "predicted_away_score": 25.200000762939453,
    "predicted_margin": -0.8578978180885315,
    "ai_spread": 0.8578978180885315,
    "vegas_spread": -3.0,
    "spread_difference": 3.9000000953674316,
    "total_line": 49.5,
    "key_factors": {
      "home_epa": 0,
      "away_epa": 0,
      "epa_advantage": 0,
      "home_recent_epa": 0,
      "away_recent_epa": 0
    },
    "game_id": "2025_11_SEA_LA",
    "season": 2025,
    "week": 11,
    "game_date": "2025-11-16",
    "kickoff_time": null,
    "status": "final",
    "actual_home_score": 21,
    "actual_away_score": 19,
    "actual_winner": "LA",
    "correct": false
  },
  {
    "home_team": "CLE",
    "away_team": "BAL",
    "win_model_prediction": "CLE",
    "home_win_prob": 0.6825392842292786,
    "away_win_prob": 0.31746071577072144,
    "confidence": 0.6825392842292786,
    "predicted_winner": "CLE",
    "predicted_home_score": 22.600000381469727,
    "predicted_away_score": 14.899999618530273,
    "predicted_margin": 7.753675937652588,
    "ai_spread": -7.753675937652588,
    "vegas_spread": 7.5,
    "spread_difference": -15.300000190734863,
    "total_line": 37.5,
    "key_factors": {
      "home_epa": 0,
      "away_epa": 0,
      "epa_advantage": 0,
      "home_recent_epa": 0,
      "away_recent_epa": 0
    },
    "game_id": "2025_11_BAL_CLE",
    "season": 2025,
    "week": 11,
    "game_date": "2025-11-16",
    "kickoff_time": null,
    "status": "final",
    "actual_home_score": 16,
    "actual_away_score": 23,
    "actual_winner": "BAL",
    "correct": false
  },
  {
    "home_team": "DEN",
    "away_team": "KC",
    "win_model_prediction": "DEN",
    "home_win_prob": 0.7714524865150452,
    "away_win_prob": 0.22854751348495483,
    "confidence": 0.7714524865150452,
    "predicted_winner": "DEN",
    "predicted_home_score": 29.100000381469727,
    "predicted_away_score": 15.399999618530273,
    "predicted_margin": 13.622705459594727,
    "ai_spread": -13.622705459594727,
    "vegas_spread": 3.5,
    "spread_difference": -17.100000381469727,
    "total_line": 44.5,
    "key_factors": {
      "home_epa": 0,
      "away_epa": 0,
      "epa_advantage": 0,
      "home_recent_epa": 0,
      "away_recent_epa": 0
    },
    "game_id": "2025_11_KC_DEN",
    "season": 2025,
    "week": 11,
    "game_date": "2025-11-16",
    "kickoff_time": null,
    "status": "final",
    "actual_home_score": 22,
    "actual_away_score": 19,
    "actual_winner": "DEN",
    "correct": true
  },
  {
    "home_team": "PHI",
    "away_team": "DET",
    "win_model_prediction": "DET",
    "home_win_prob": 0.16179431974887848,
    "away_win_prob": 0.8382056951522827,
    "confidence": 0.8382056951522827,
    "predicted_winner": "PHI",
    "predicted_home_score": 25.100000381469727,
    "predicted_away_score": 21.399999618530273,
    "predicted_margin": 3.7591195106506348,
    "ai_spread": -3.7591195106506348,
    "vegas_spread": -2.5,
    "spread_difference": -1.2999999523162842,
    "total_line": 46.5,
    "key_factors": {
      "home_epa": 0,
      "away_epa": 0,
      "epa_advantage": 0,
      "home_recent_epa": 0,
      "away_recent_epa": 0
    },
    "game_id": "2025_11_DET_PHI",
    "season": 2025,
    "week": 11,
    "game_date": "2025-11-16",
    "kickoff_time": null,
    "status": "final",
    "actual_home_score": 16,
    "actual_away_score": 9,
    "actual_winner": "PHI",
    "correct": true
  },
  {
    "home_team": "JAX",
    "away_team": "LAC",
    "win_model_prediction": "LAC",
    "home_win_prob": 0.22697211802005768,
    "away_win_prob": 0.7730278968811035,
    "confidence": 0.7730278968811035,
    "predicted_winner": "LAC",
    "predicted_home_score": 21.299999237060547,
    "predicted_away_score": 22.200000762939453,
    "predicted_margin": -0.8481809496879578,
    "ai_spread": 0.8481809496879578,
    "vegas_spread": 3.0,
    "spread_difference": -2.200000047683716,
    "total_line": 43.5,
    "key_factors": {
      "home_epa": 0,
      "away_epa": 0,
      "epa_advantage": 0,
      "home_recent_epa": 0,
      "away_recent_epa": 0
    },
    "game_id": "2025_11_LAC_JAX",
    "season": 2025,
    "week": 11,
    "game_date": "2025-11-16",
    "kickoff_time": null,
    "status": "final",
    "actual_home_score": 35,
    "actual_away_score": 6,
    "actual_winner": "JAX",
    "correct": false
  },
  {
    "home_team": "MIN",
    "away_team": "CHI",
    "win_model_prediction": "CHI",
    "home_win_prob": 0.0618438757956028,
    "away_win_prob": 0.9381561279296875,
    "confidence": 0.9381561279296875,
    "predicted_winner": "CHI",
    "predicted_home_score": 22.399999618530273,
    "predicted_away_score": 25.100000381469727,
    "predicted_margin": -2.7852718830108643,
    "ai_spread": 2.7852718830108643,
    "vegas_spread": -3.0,
    "spread_difference": 5.800000190734863,
    "total_line": 47.5,
    "key_factors": {
      "home_epa": 0,
      "away_epa": 0,
      "epa_advantage": 0,
      "home_recent_epa": 0,
      "away_recent_epa": 0
    },
    "game_id": "2025_11_CHI_MIN",
    "season": 2025,
    "week": 11,
    "game_date": "2025-11-16",
    "kickoff_time": null,
    "status": "final",
    "actual_home_score": 17,
    "actual_away_score": 19,
    "actual_winner": "CHI",
    "correct": true
  },
  {
    "home_team": "MIA",
    "away_team": "WAS",
    "win_model_prediction": "WAS",
    "home_win_prob": 0.13560867309570312,
    "away_win_prob": 0.8643913269042969,
    "confidence": 0.8643913269042969,
    "predicted_winner": "MIA",
    "predicted_home_score": 24.899999618530273,
    "predicted_away_score": 22.600000381469727,
    "predicted_margin": 2.2793424129486084,
    "ai_spread": -2.2793424129486084,
    "vegas_spread": -2.5,
    "spread_difference": 0.20000000298023224,
    "total_line": 47.5,
    "key_factors": {
      "home_epa": 0,
      "away_epa": 0,
      "epa_advantage": 0,
      "home_recent_epa": 0,
      "away_recent_epa": 0
    },
    "game_id": "2025_11_WAS_MIA",
    "season": 2025,
    "week": 11,
    "game_date": "2025-11-16",
    "kickoff_time": null,
    "status": "final",
    "actual_home_score": 16,
    "actual_away_score": 13,
    "actual_winner": "MIA",
    "correct": true
  },
  {
    "home_team": "ATL",
    "away_team": "CAR",
    "win_model_prediction": "CAR",
    "home_win_prob": 0.037628669291734695,
    "away_win_prob": 0.9623713493347168,
    "confidence": 0.9623713493347168,
    "predicted_winner": "CAR",
    "predicted_home_score": 21.0,
    "predicted_away_score": 21.5,
    "predicted_margin": -0.533085286617279,
    "ai_spread": 0.533085286617279,
    "vegas_spread": -4.5,
    "spread_difference": 5.0,
    "total_line": 42.5,
    "key_factors": {
      "home_epa": 0,
      "away_epa": 0,
      "epa_advantage": 0,
      "home_recent_epa": 0,
      "away_recent_epa": 0
    },
    "game_id": "2025_11_CAR_ATL",
    "season": 2025,
    "week": 11,
    "game_date": "2025-11-16",
    "kickoff_time": null,
    "status": "final",
    "actual_home_score": 27,
    "actual_away_score": 30,
    "actual_winner": "CAR",
    "correct": true
  },
  {
    "home_team": "BUF",
    "away_team": "TB",
    "win_model_prediction": "TB",
    "home_win_prob": 0.005462849047034979,
    "away_win_prob": 0.9945371747016907,
    "confidence": 0.9945371747016907,
    "predicted_winner": "TB",
    "predicted_home_score": 18.200000762939453,
    "predicted_away_score": 28.299999237060547,
    "predicted_margin": -10.09270191192627,
    "ai_spread": 10.09270191192627,
    "vegas_spread": -6.0,
    "spread_difference": 16.100000381469727,
    "total_line": 46.5,
    "key_factors": {
      "home_epa": 0,
      "away_epa": 0,
      "epa_advantage": 0,
      "home_recent_epa": 0,
      "away_recent_epa": 0
    },
    "game_id": "2025_11_TB_BUF",
    "season": 2025,
    "week": 11,
    "game_date": "2025-11-16",
    "kickoff_time": null,
    "status": "final",
    "actual_home_score": 44,
    "actual_away_score": 32,
    "actual_winner": "BUF",
    "correct": false
  },
  {
    "home_team": "LV",
    "away_team": "DAL",
    "win_model_prediction": "LV",
    "home_win_prob": 0.893168568611145,
    "away_win_prob": 0.10683143138885498,
    "confidence": 0.893168568611145,
    "predicted_winner": "LV",
    "predicted_home_score": 30.799999237060547,
    "predicted_away_score": 17.700000762939453,
    "predicted_margin": 13.181015968322754,
    "ai_spread": -13.181015968322754,
    "vegas_spread": 3.5,
    "spread_difference": -16.700000762939453,
    "total_line": 48.5,
    "key_factors": {
      "home_epa": 0,
      "away_epa": 0,
      "epa_advantage": 0,
      "home_recent_epa": 0,
      "away_recent_epa": 0
    },
    "game_id": "2025_11_DAL_LV",
    "season": 2025,
    "week": 11,
    "game_date": "2025-11-17",
    "kickoff_time": null,
    "status": "final",
    "actual_home_score": 16,
    "actual_away_score": 33,
    "actual_winner": "DAL",
    "correct": false
  }
]