[
  {
    "home_team": "HOU",
    "away_team": "BUF",
    "win_model_prediction": "HOU",
    "home_win_prob": 0.8496132493019104,
    "away_win_prob": 0.1503867506980896,
    "confidence": 0.8496132493019104,
    "predicted_winner": "HOU",
    "predicted_home_score": 30.399999618530273,
    "predicted_away_score": 13.100000381469727,
    "predicted_margin": 17.38616943359375,
    "ai_spread": -17.38616943359375,
    "vegas_spread": 5.5,
    "spread_difference": -22.899999618530273,
    "total_line": 43.5,
    "key_factors": {
      "home_epa": 0,
      "away_epa": 0,
      "epa_advantage": 0,
      "home_recent_epa": 0,
      "away_recent_epa": 0
    },
    "game_id": "2025_12_BUF_HOU",
    "season": 2025,
    "week": 12,
    "game_date": "2025-11-20",
    "kickoff_time": null,
    "status": "final",
    "actual_home_score": 23,
    "actual_away_score": 19,
    "actual_winner": "HOU",
    "correct": true
  },
  {
    "home_team": "ARI",
    "away_team": "JAX",
    "win_model_prediction": "JAX",
    "home_win_prob": 0.24744698405265808,
    "away_win_prob": 0.7525529861450195,
    "confidence": 0.7525529861450195,
    "predicted_winner": "ARI",
    "predicted_home_score": 26.600000381469727,
    "predicted_away_score": 20.899999618530273,
    "predicted_margin": 5.601943492889404,
    "ai_spread": -5.601943492889404,
    "vegas_spread": 2.5,
    "spread_difference": -8.100000381469727,
    "total_line": 47.5,
    "key_factors": {
      "home_epa": 0,
      "away_epa": 0,
      "epa_advantage": 0,
      "home_recent_epa": 0,
      "away_recent_epa": 0
    },
    "game_id": "2025_12_JAX_ARI",
    "season": 2025,
    "week": 12,
    "game_date": "2025-11-23",
    "kickoff_time": null,
    "status": "final",
    "actual_home_score": 24,
    "actual_away_score": 27,
    "actual_winner": "JAX",
    "correct": false
  },
  {
    "home_team": "LA",
    "away_team": "TB",
    "win_model_prediction": "TB",
    "home_win_prob": 0.007588541135191917,
    "away_win_prob": 0.9924114346504211,
    "confidence": 0.9924114346504211,
    "predicted_winner": "TB",
    "predicted_home_score": 17.0,
    "predicted_away_score": 32.5,
    "predicted_margin": -15.568049430847168,
    "ai_spread": 15.568049430847168,
    "vegas_spread": -7.0,
    "spread_difference": 22.600000381469727,
    "total_line": 49.5,
    "key_factors": {
      "home_epa": 0,
      "away_epa": 0,
      "epa_advantage": 0,
      "home_recent_epa": 0,
      "away_recent_epa": 0
    },
    "game_id": "2025_12_TB_LA",
    "season": 2025,
    "week": 12,
    "game_date": "2025-11-23",
    "kickoff_time": null,
    "status": "final",
    "actual_home_score": 34,
    "actual_away_score": 7,
    "actual_winner": "LA",
    "correct": false
  },
  {
    "home_team": "BAL",
    "away_team": "NYJ",
    "win_model_prediction": "NYJ",
    "home_win_prob": 0.01756615750491619,
    "away_win_prob": 0.9824338555335999,
    "confidence": 0.9824338555335999,
    "predicted_winner": "NYJ",
    "predicted_home_score": 16.100000381469727,
    "predicted_away_score": 28.399999618530273,
    "predicted_margin": -12.299570083618164,
    "ai_spread": 12.299570083618164,
    "vegas_spread": -14.0,
    "spread_difference": 26.299999237060547,
    "total_line": 44.5,
    "key_factors": {
      "home_epa": 0,
      "away_epa": 0,
      "epa_advantage": 0,
      "home_recent_epa": 0,
      "away_recent_epa": 0
    },
    "game_id": "2025_12_NYJ_BAL",
    "season": 2025,
    "week": 12,
    "game_date": "2025-11-23",
    "kickoff_time": null,
    "status": "final",
    "actual_home_score": 23,
    "actual_away_score": 10,
    "actual_winner": "BAL",
    "correct": false
  },
  {
    "home_team": "CHI",
    "away_team": "PIT",
    "win_model_prediction": "PIT",
    "home_win_prob": 0.062391750514507294,
    "away_win_prob": 0.9376082420349121,
    "confidence": 0.9376082420349121,
    "predicted_winner": "PIT",
    "predicted_home_score": 23.100000381469727,
    "predicted_away_score": 23.399999618530273,
    "predicted_margin": -0.21657024323940277,
    "ai_spread": 0.21657024323940277,
    "vegas_spread": -3.0,
    "spread_difference": 3.200000047683716,
    "total_line": 46.5,
    "key_factors": {
      "home_epa": 0,
      "away_epa": 0,
      "epa_advantage": 0,
      "home_recent_epa": 0,
      "away_recent_epa": 0
    },
    "game_id": "2025_12_PIT_CHI",
    "season": 2025,
    "week": 12,
    "game_date": "2025-11-23",
    "kickoff_time": null,
    "status": "final",
    "actual_home_score": 31,
    "actual_away_score": 28,
    "actual_winner": "CHI",
    "correct": false
  },
  {
    "home_team": "CIN",
    "away_team": "NE",
    "win_model_prediction": "CIN",
    "home_win_prob": 0.7831454873085022,
    "away_win_prob": 0.2168545126914978,
    "confidence": 0.7831454873085022,
    "predicted_winner": "CIN",
    "predicted_home_score": 30.299999237060547,
    "predicted_away_score": 20.200000762939453,
    "predicted_margin": 10.105565071105957,
    "ai_spread": -10.105565071105957,
    "vegas_spread": 7.5,
    "spread_difference": -17.600000381469727,
    "total_line": 50.5,
    "key_factors": {
      "home_epa": 0,
      "away_epa": 0,
      "epa_advantage": 0,
      "home_recent_epa": 0,
      "away_recent_epa": 0
    },
    "game_id": "2025_12_NE_CIN",
    "season": 2025,
    "week": 12,
    "game_date": "2025-11-23",
    "kickoff_time": null,
    "status": "final",
    "actual_home_score": 20,
    "actual_away_score": 26,
    "actual_winner": "NE",
    "correct": false
  },
  {
    "home_team": "DET",
    "away_team": "NYG",
    "win_model_prediction": "NYG",
    "home_win_prob": 0.009677511639893055,
    "away_win_prob": 0.990322470664978,
    "confidence": 0.990322470664978,
    "predicted_winner": "NYG",
    "predicted_home_score": 19.600000381469727,
    "predicted_away_score": 30.899999618530273,
    "predicted_margin": -11.300966262817383,
    "ai_spread": 11.300966262817383,
    "vegas_spread": -14.0,
    "spread_difference": 25.299999237060547,
    "total_line": 50.5,
    "key_factors": {
      "home_epa": 0,
      "away_epa": 0,
      "epa_advantage": 0,
      "home_recent_epa": 0,
      "away_recent_epa": 0
    },
    "game_id": "2025_12_NYG_DET",
    "season": 2025,
    "week": 12,
    "game_date": "2025-11-23",
    "kickoff_time": null,
    "status": "final",
    "actual_home_score": 34,
    "actual_away_score": 27,
    "actual_winner": "DET",
    "correct": false
  },
  {
    "home_team": "GB",
    "away_team": "MIN",
    "win_model_prediction": "MIN",
    "home_win_prob": 0.0050931330770254135,
    "away_win_prob": 0.9949068427085876,
    "confidence": 0.9949068427085876,
    "predicted_winner": "MIN",
    "predicted_home_score": 12.899999618530273,
    "predicted_away_score": 28.600000381469727,
    "predicted_margin": -15.728753089904785,
    "ai_spread": 15.728753089904785,
    "vegas_spread": -6.5,
    "spread_difference": 22.200000762939453,
    "total_line": 41.5,
    "key_factors": {
      "home_epa": 0,
      "away_epa": 0,
      "epa_advantage": 0,
      "home_recent_epa": 0,
      "away_recent_epa": 0
    },
    "game_id": "2025_12_MIN_GB",
    "season": 2025,
    "week": 12,
    "game_date": "2025-11-23",
    "kickoff_time": null,
    "status": "final",
    "actual_home_score": 23,
    "actual_away_score": 6,
    "actual_winner": "GB",
    "correct": false
  },
  {
    "home_team": "LV",
    "away_team": "CLE",
    "win_model_prediction": "CLE",
    "home_win_prob": 0.13546989858150482,
    "away_win_prob": 0.864530086517334,
    "confidence": 0.864530086517334,
    "predicted_winner": "LV",
    "predicted_home_score": 18.799999237060547,
    "predicted_away_score": 16.700000762939453,
    "predicted_margin": 2.098233461380005,
    "ai_spread": -2.098233461380005,
    "vegas_spread": -3.0,
    "spread_difference": 0.8999999761581421,
    "total_line": 35.5,
    "key_factors": {
      "home_epa": 0,
      "away_epa": 0,
      "epa_advantage": 0,
      "home_recent_epa": 0,
      "away_recent_epa": 0
    },
    "game_id": "2025_12_CLE_LV",
    "season": 2025,
    "week": 12,
    "game_date": "2025-11-23",
    "kickoff_time": null,
    "status": "final",
    "actual_home_score": 10,
    "actual_away_score": 24,
    "actual_winner": "CLE",
    "correct": false
  },
  {
    "home_team": "DAL",
    "away_team": "PHI",
    "win_model_prediction": "PHI",
    "home_win_prob": 0.23903444409370422,
    "away_win_prob": 0.7609655857086182,
    "confidence": 0.7609655857086182,
    "predicted_winner": "DAL",
    "predicted_home_score": 26.100000381469727,
    "predicted_away_score": 21.399999618530273,
    "predicted_margin": 4.74473762512207,
    "ai_spread": -4.74473762512207,
    "vegas_spread": 3.0,
    "spread_difference": -7.699999809265137,
    "total_line": 47.5,
    "key_factors": {
      "home_epa": 0,
      "away_epa": 0,
      "epa_advantage": 0,
      "home_recent_epa": 0,
      "away_recent_epa": 0
    },
    "game_id": "2025_12_PHI_DAL",
    "season": 2025,
    "week": 12,
    "game_date": "2025-11-23",
    "kickoff_time": null,
    "status": "final",
    "actual_home_score": 24,
    "actual_away_score": 21,
    "actual_winner": "DAL",
    "correct": true
  },
  {
    "home_team": "NO",
    "away_team": "ATL",
    "win_model_prediction": "ATL",
    "home_win_prob": 0.04615457355976105,
    "away_win_prob": 0.9538454413414001,
    "confidence": 0.9538454413414001,
    "predicted_winner": "NO",
    "predicted_home_score": 22.200000762939453,
    "predicted_away_score": 19.299999237060547,
    "predicted_margin": 2.847527265548706,
    "ai_spread": -2.847527265548706,
    "vegas_spread": -1.5,
    "spread_difference": -1.2999999523162842,
    "total_line": 41.5,
    "key_factors": {
      "home_epa": 0,
      "away_epa": 0,
      "epa_advantage": 0,
      "home_recent_epa": 0,
      "away_recent_epa": 0
    },
    "game_id": "2025_12_ATL_NO",
    "season": 2025,
    "week": 12,
    "game_date": "2025-11-23",
    "kickoff_time": null,
    "status": "final",
    "actual_home_score": 10,
    "actual_away_score": 24,
    "actual_winner": "ATL",
    "correct": false
  },
  {
    "home_team": "KC",
    "away_team": "IND",
    "win_model_prediction": "IND",
    "home_win_prob": 0.381211519241333,
    "away_win_prob": 0.618788480758667,
    "confidence": 0.618788480758667,
    "predicted_winner": "KC",
    "predicted_home_score": 27.899999618530273,
    "predicted_away_score": 22.600000381469727,
    "predicted_margin": 5.309066295623779,
    "ai_spread": -5.309066295623779,
    "vegas_spread": -3.5,
    "spread_difference": -1.7999999523162842,
    "total_line": 50.5,
    "key_factors": {
      "home_epa": 0,
      "away_epa": 0,
      "epa_advantage": 0,
      "home_recent_epa": 0,
      "away_recent_epa": 0
    },
    "game_id": "2025_12_IND_KC",
    "season": 2025,
    "week": 12,
    "game_date": "2025-11-23",
    "kickoff_time": null,
    "status": "final",
    "actual_home_score": 23,
    "actual_away_score": 20,
    "actual_winner": "KC",
    "correct": true
  },
  {
    "home_team": "TEN",
    "away_team": "SEA",
    "win_model_prediction": "TEN",
    "home_win_prob": 0.876059353351593,
    "away_win_prob": 0.12394064664840698,
    "confidence": 0.876059353351593,
    "predicted_winner": "TEN",
    "predicted_home_score": 21.399999618530273,
    "predicted_away_score": 20.100000381469727,
    "predicted_margin": 1.3053544759750366,
    "ai_spread": -1.3053544759750366,
    "vegas_spread": 12.5,
    "spread_difference": -13.800000190734863,
    "total_line": 41.5,
    "key_factors": {
      "home_epa": 0,
      "away_epa": 0,
      "epa_advantage": 0,
      "home_recent_epa": 0,
      "away_recent_epa": 0
    },
    "game_id": "2025_12_SEA_TEN",
    "season": 2025,
    "week": 12,
    "game_date": "2025-11-23",
    "kickoff_time": null,
    "status": "final",
    "actual_home_score": 24,
    "actual_away_score": 30,
    "actual_winner": "SEA",
    "correct": false
  },
  {
    "home_team": "SF",
    "away_team": "CAR",
    "win_model_prediction": "CAR",
    "home_win_prob": 0.002967130858451128,
    "away_win_prob": 0.997032880783081,
    "confidence": 0.997032880783081,
    "predicted_winner": "CAR",
    "predicted_home_score": 17.0,
    "predicted_away_score": 31.5,
    "predicted_margin": -14.546858787536621,
    "ai_spread": 14.546858787536621,
    "vegas_spread": -7.5,
    "spread_difference": 22.0,
    "total_line": 48.5,
    "key_factors": {
      "home_epa": 0,
      "away_epa": 0,
      "epa_advantage": 0,
      "home_recent_epa": 0,
      "away_recent_epa": 0
    },
    "game_id": "2025_12_CAR_SF",
    "season": 2025,
    "week": 12,
    "game_date": "2025-11-24",
    "kickoff_time": null,
    "status": "final",
    "actual_home_score": 20,
    "actual_away_score": 9,
    "actual_winner": "SF",
    "correct": false
  }
]